protect/__init__.py
protect/distributions.py
protect/inference.py
protect/models.py
protect/utils.py
protectcode-0.1.0.dist-info/METADATA
protectcode-0.1.0.dist-info/WHEEL
protectcode-0.1.0.dist-info/entry_points.txt
protectcode-0.1.0.dist-info/licenses/LICENSE
protectcode-0.1.0.dist-info/RECORD
