Metadata-Version: 2.1
Name: protectcode
Version: 0.1.0
Summary: Implementation of the PROTECT method
Requires-Python: >=3.11
Requires-Dist: arviz>=0.22.0
Requires-Dist: funsor>=0.4.5
Requires-Dist: numpyro>=0.19.0
Requires-Dist: pandas>=2.3.2
Requires-Dist: pyyaml>=6.0.2
Requires-Dist: tfp-nightly[jax]>=0.26.0.dev20250827
